.gitlab-ci.yml
.travis.yml
CHANGES.rst
CONTRIBUTORS.rst
DEVELOP.rst
LICENSE.GPL
LICENSE.rst
MANIFEST.in
README.rst
constraints.txt
constraints_plone43.txt
constraints_plone50.txt
constraints_plone51.txt
constraints_plone52.txt
requirements.txt
setup.cfg
setup.py
tox.ini
docs/collective.addons.pdf
docs/conf.py
docs/index.rst
docs/html/addnewaddoncenter.html
docs/html/addnewaddonlinkedrelease.html
docs/html/addnewaddonproject.html
docs/html/addnewaddonrelease.html
docs/html/configuration.html
docs/html/genindex.html
docs/html/index.html
docs/html/installation.html
docs/html/messaging.html
docs/html/publishaddonproject.html
docs/html/publishaddonrelease.html
docs/html/search.html
docs/html/searchindex.js
docs/html/_images/addon_center_form01.png
docs/html/_images/addon_center_form02.png
docs/html/_images/addon_center_form03.png
docs/html/_images/addon_center_sharing.png
docs/html/_images/addon_linked_release_form01.png
docs/html/_images/addon_linked_release_form02.png
docs/html/_images/addon_linked_release_form03.png
docs/html/_images/addon_linked_release_form04.png
docs/html/_images/addon_project_form01.png
docs/html/_images/addon_project_form02.png
docs/html/_images/addon_project_form03.png
docs/html/_images/addon_project_form04.png
docs/html/_images/addon_release_form01.png
docs/html/_images/addon_release_form02.png
docs/html/_images/addon_release_form03.png
docs/html/_images/addon_release_form04.png
docs/html/_images/addon_release_publish1.png
docs/html/_images/configuration_collective_addons.png
docs/html/_images/configuration_collective_addons_form02.png
docs/html/_images/configuration_collective_addons_form03.png
docs/html/_images/create_addon_center.png
docs/html/_images/create_addon_linked_release.png
docs/html/_images/create_addon_project.png
docs/html/_images/create_addon_release.png
docs/html/_images/install_collective_addon.png
docs/html/_images/navigation_add_addon_center.png
docs/html/_sources/addnewaddoncenter.rst.txt
src/collective.addons.egg-info/PKG-INFO
src/collective.addons.egg-info/SOURCES.txt
src/collective.addons.egg-info/dependency_links.txt
src/collective.addons.egg-info/entry_points.txt
src/collective.addons.egg-info/namespace_packages.txt
src/collective.addons.egg-info/not-zip-safe
src/collective.addons.egg-info/requires.txt
src/collective.addons.egg-info/top_level.txt
