Metadata-Version: 2.1
Name: collective.addons
Version: 3.1
Summary: Plone add-on to host add-ons / extensions of a software
Home-page: https://github.com/collective/collective.addons
Author: Andreas Mantke
Author-email: maand@gmx.de
License: GPL version 2
Project-URL: PyPI, https://pypi.python.org/pypi/collective.addons
Project-URL: Source, https://github.com/collective/collective.addons
Project-URL: Tracker, https://github.com/collective/collective.addons/issues
Keywords: Python Plone
Platform: UNKNOWN
Classifier: Environment :: Web Environment
Classifier: Framework :: Plone
Classifier: Framework :: Plone :: Addon
Classifier: Framework :: Plone :: 5.2
Classifier: Programming Language :: Python
Classifier: Programming Language :: Python :: 2.7
Classifier: Programming Language :: Python :: 3.6
Classifier: Programming Language :: Python :: 3.7
Classifier: Operating System :: OS Independent
Classifier: License :: OSI Approved :: GNU General Public License v2 (GPLv2)
Requires-Python: ==2.7, >=3.6
Provides-Extra: test
